redis_annex/__about__.py
redis_annex/__init__.py
redis_annex-0.2.5.dist-info/METADATA
redis_annex-0.2.5.dist-info/WHEEL
redis_annex-0.2.5.dist-info/licenses/LICENSE
redis_annex-0.2.5.dist-info/RECORD
