Metadata-Version: 2.1
Name: redis-annex
Version: 0.2.5
Summary: supplements for py-redis
Project-URL: Documentation, https://github.com/greyltc-org/redis-annex#readme
Project-URL: Issues, https://github.com/greyltc-org/redis-annex/issues
Project-URL: Source, https://github.com/greyltc-org/redis-annex
Author-email: Greyson Christoforo <grey@christoforo.net>
License-File: LICENSE
Classifier: Development Status :: 4 - Beta
Classifier: Programming Language :: Python
Classifier: Programming Language :: Python :: 3.7
Classifier: Programming Language :: Python :: 3.8
Classifier: Programming Language :: Python :: 3.9
Classifier: Programming Language :: Python :: 3.10
Classifier: Programming Language :: Python :: 3.11
Classifier: Programming Language :: Python :: Implementation :: CPython
Classifier: Programming Language :: Python :: Implementation :: PyPy
Requires-Python: >=3.7
Requires-Dist: redis
